{
  "project_info": {
    "project_number": "364787747530",
    "project_id": "ai-dream-interpretation-9d22c",
    "storage_bucket": "ai-dream-interpretation-9d22c.firebasestorage.app"
  },
  "client": [
    {
      "client_info": {
        "mobilesdk_app_id": "1:364787747530:android:43e48bd3fabf6a1b360233",
        "android_client_info": {
          "package_name": "com.jvai.ai_dream_interpretation"
        }
      },
      "oauth_client": [
        {
          "client_id": "364787747530-9r155qeo4vbuj1739qhr0be1l0u4roai.apps.googleusercontent.com",
          "client_type": 1,
          "android_info": {
            "package_name": "com.jvai.ai_dream_interpretation",
            "certificate_hash": "d6f88727a3658a292d694fded4bbbbb13a6b86c5"
          }
        },
        {
          "client_id": "364787747530-o760fegu74t5d8gef348lngppfojh156.apps.googleusercontent.com",
          "client_type": 3
        }
      ],
      "api_key": [
        {
          "current_key": "AIzaSyDIzItmEHtmaCTHBiBqYrTc23CE5EGPV38"
        }
      ],
      "services": {
        "appinvite_service": {
          "other_platform_oauth_client": [
            {
              "client_id": "364787747530-o760fegu74t5d8gef348lngppfojh156.apps.googleusercontent.com",
              "client_type": 3
            }
          ]
        }
      }
    }
  ],
  "configuration_version": "1"
}